Metadata-Version: 1.1
Name: pivot-table
Version: 0.0.1
Summary: the pivot dash component
Home-page: UNKNOWN
Author: kalimuthu periyasamy <1995kalimuthu@gmail.com>
Author-email: UNKNOWN
License: MIT
Platform: UNKNOWN
Classifier: Framework :: Dash
